MANIFEST.in
README.md
setup.py
alphaspace2/Cluster.py
alphaspace2/Community.py
alphaspace2/Configs.py
alphaspace2/Features.py
alphaspace2/Snapshot.py
alphaspace2/Trajectory.py
alphaspace2/View.py
alphaspace2/VinaScoring.py
alphaspace2/__init__.py
alphaspace2/functions.py
alphaspace2.egg-info/PKG-INFO
alphaspace2.egg-info/SOURCES.txt
alphaspace2.egg-info/dependency_links.txt
alphaspace2.egg-info/not-zip-safe
alphaspace2.egg-info/requires.txt
alphaspace2.egg-info/top_level.txt
alphaspace2/data/AS_Chimera_beta.py
alphaspace2/data/AS_chimera_alpha.py
alphaspace2/data/amber_types_fine.dat
alphaspace2/data/autodock_atom_type_info.dat
alphaspace2/data/colors_chimera.txt
alphaspace2/data/colors_table.txt
alphaspace2/data/hp_types_dict.dat
alphaspace2/data/typing_from_pdb.dat
alphaspace2/data/vina_params.dat
bin/alphaspace2