Metadata-Version: 1.1
Name: alphaspace2
Version: 0.1.2
Summary: Protein topographical mapping tool
Home-page: http://github.com/lenhsherr/alphaspace2
Author: Haotian Li
Author-email: hl2368@nyu.edu
License: gpl-3.0
Platform: UNKNOWN
Classifier: Programming Language :: Python :: 3
Classifier: Operating System :: OS Independent
